gamma_simulator/__init__.py
gamma_simulator/gamma_simulator.py
gamma_simulator-1.0.7.dist-info/LICENSE.txt
gamma_simulator-1.0.7.dist-info/METADATA
gamma_simulator-1.0.7.dist-info/WHEEL
gamma_simulator-1.0.7.dist-info/top_level.txt
gamma_simulator-1.0.7.dist-info/RECORD
