Metadata-Version: 2.1
Name: gamma_simulator
Version: 1.0.7
Summary: a gamma simulator 
Author: Chen_zk
Author-email: 
License: BSD-3-Clause
Keywords: python,gamma,pulse,simulate
Classifier: Development Status :: 1 - Planning
Classifier: Intended Audience :: Developers
Classifier: Programming Language :: Python :: 3
Classifier: Operating System :: Unix
Classifier: Operating System :: MacOS :: MacOS X
Classifier: Operating System :: Microsoft :: Windows
License-File: LICENSE.txt
Requires-Dist: numpy
Requires-Dist: scipy
Requires-Dist: matplotlib
Requires-Dist: urllib3
